__init__.py
chatgptcli/__init__.py
chatgptcli/main.py
chatgptcli/classes/chat.py
chatgptcli/classes/openai.py
chatgptcli/classes/spinner.py
chatgptcli-1.6.0.dist-info/LICENSE
chatgptcli-1.6.0.dist-info/METADATA
chatgptcli-1.6.0.dist-info/WHEEL
chatgptcli-1.6.0.dist-info/top_level.txt
chatgptcli-1.6.0.dist-info/RECORD
