Metadata-Version: 2.1
Name: chatgptcli
Version: 1.6.0
Summary: The command line wrapper for ChatGPT by OpenAI
Author-email: Gautam Veldanda <veldandaga@outlook.com>
Project-URL: Homepage, https://github.com/veldandaga/chatgptcli
Project-URL: Bug Tracker, https://github.com/veldandaga/chatgptcli/issues
Classifier: Programming Language :: Python :: 3
Classifier: License :: OSI Approved :: MIT License
Classifier: Operating System :: OS Independent
Requires-Python: >=3.9
License-File: LICENSE
Requires-Dist: tls-client
Requires-Dist: requests
Requires-Dist: colorama
Requires-Dist: svglib
Requires-Dist: bs4
Requires-Dist: reportlab
